{
  "appInfo" : {
    "build" : "251.25775",
    "buildDate" : "2025-06-05T14:02:41.995Z[Etc/UTC]",
    "productCode" : "QDJVMC",
    "generated" : "2025-06-05T14:02:56.800713803Z",
    "os" : "Linux 6.10.14-linuxkit",
    "runtime" : "JetBrains s.r.o. 21.0.7 21.0.7+9-b895.115"
  },
  "runtimeInfo" : {
    "maxMemory" : 5754585088,
    "numberOfProcessors" : 24,
    "maxNumberOfIndexingThreads" : 24,
    "maxSizeOfFileForIntelliSense" : 2560000,
    "maxSizeOfFileForContentLoading" : 20971520
  },
  "type" : "Scanning",
  "projectIndexingActivityHistory" : {
    "projectName" : "SolaceCore",
    "times" : {
      "scanningReason" : "Merged changes in: \"JDK 19 /root/.jdks/corretto-19.0.2\" with changes in: \"JDK 19 /root/.jdks/corretto-19.0.2\" with changes in: \"JDK 19 /root/.jdks/corretto-19.0.2\"",
      "scanningType" : "PARTIAL",
      "scanningId" : 1,
      "creatingIteratorsTime" : 0,
      "concurrentHandlingWallTimeWithoutPauses" : 0,
      "concurrentHandlingWallTimeWithPauses" : 0,
      "concurrentHandlingSumOfThreadTimesWithPauses" : 772831999,
      "concurrentIterationAndScannersApplicationSumOfThreadTimesWithPauses" : 161090291,
      "concurrentFileCheckSumOfThreadTimesWithPauses" : 611571458,
      "delayedPushPropertiesStageTime" : 0,
      "indexExtensionsTime" : 4669379,
      "dumbWallTimeWithPauses" : 0,
      "dumbWallTimeWithoutPauses" : 0,
      "updatingStart" : "2025-06-05T14:02:56.395118469Z",
      "updatingEnd" : "2025-06-05T14:02:56.799786469Z",
      "totalWallTimeWithPauses" : 404668000,
      "wallTimeOnPause" : 454625,
      "isCancelled" : false,
      "totalWallTimeWithoutPauses" : 404213375
    },
    "fileCount" : {
      "numberOfFileProviders" : 2,
      "numberOfScannedFiles" : 42668,
      "numberOfFilesIndexedByInfrastructureExtensionsDuringScan" : 0,
      "numberOfFilesScheduledForIndexingAfterScan" : 42334
    },
    "scanningStatistics" : [ {
      "providerName" : "JDK 19 /root/.jdks/corretto-19.0.2",
      "numberOfScannedFiles" : 21823,
      "numberOfSkippedFiles" : 146,
      "numberOfFilesForIndexing" : 21769,
      "numberOfFilesFullyIndexedByInfrastructureExtensions" : 0,
      "filesFullyIndexedByInfrastructureExtensions" : [ ],
      "statusTime" : 267960910,
      "totalOneThreadTimeWithPauses" : 387434458,
      "iterationAndScannersApplicationTime" : 81099500,
      "filesCheckTime" : 306268583,
      "timeProcessingUpToDateFiles" : 0,
      "timeUpdatingContentLessIndexes" : 0,
      "timeIndexingWithoutContentViaInfrastructureExtension" : 2516721,
      "roots" : [ ]
    }, {
      "providerName" : "JDK 19 /root/.jdks/corretto-19.0.2",
      "numberOfScannedFiles" : 20845,
      "numberOfSkippedFiles" : 64,
      "numberOfFilesForIndexing" : 20565,
      "numberOfFilesFullyIndexedByInfrastructureExtensions" : 0,
      "filesFullyIndexedByInfrastructureExtensions" : [ ],
      "statusTime" : 265418490,
      "totalOneThreadTimeWithPauses" : 385397541,
      "iterationAndScannersApplicationTime" : 79990791,
      "filesCheckTime" : 305302875,
      "timeProcessingUpToDateFiles" : 0,
      "timeUpdatingContentLessIndexes" : 0,
      "timeIndexingWithoutContentViaInfrastructureExtension" : 2152658,
      "roots" : [ ]
    } ]
  }
}